motionify/__init__.py
motionify/main.py
motionify/prompts.py
motionify-2025.12.21173502.dist-info/METADATA
motionify-2025.12.21173502.dist-info/WHEEL
motionify-2025.12.21173502.dist-info/top_level.txt
motionify-2025.12.21173502.dist-info/RECORD
