Metadata-Version: 2.4
Name: motionify
Version: 2025.12.21173502
Summary: A new package designed to facilitate the creation and control of animated characters in real-world environments by interpreting user instructions and transforming them into structured action plans. It
Author-email: motionify <hi@eugene.plus>
License: MIT
Project-URL: Homepage, https://github.com/chigwell/motionify
Requires-Python: >=3.9
Requires-Dist: langchain-llm7>=0.0.0
Requires-Dist: llmatch-messages>=0.0.0
Requires-Dist: langchain-core>=0.3.0
